AHB_Bus.v
///////////////////////////////////////////////////////////////////////////////////////////////////
//-------------------------------------------------------------------------------
//-- Title      : AHB Master Interface
//-------------------------------------------------------------------------------
//-- File       : AHB_IF.v
//-- Author     : Corporate Applications Engineering
//-- Company    : Microsemi Corporation
//-- Device     : IGLOO2
//-- Standard   : Verilog
//-------------------------------------------------------------------------------
//-- Description: This code implementes the AHB master logic to receive the read writes  
//--              from the FIC_0 and does the corresponding read or writes to other blocks.
//-------------------------------------------------------------------------------
//-- Copyright (c) 2013   Microsemi Corporation
//--                      All rights reserved.
//-------------------------------------------------------------------------------
//-- Revisions  : V1.0
//-------------------------------------------------------------------------------
/////////////////////////////////////////////////////////////////////////////////////////////////// 

module AHB_BUS( 

// Generic Signals
input      wire         HCLK,
input      wire         HRESETn,

//AHB interface to Logic
input      wire         READ,
output     reg   [15:0] DATAOUT,


// AHB Side Interfacing with FIC 
output     reg   [31:0] HADDR,
output     reg   [1:0]  HTRANS,
output     reg          HWRITE,
output     wire  [2:0]  HSIZE,
output     wire  [2:0]  HBURST,
output     wire  [3:0]  HPROT,
output     reg   [31:0] HWDATA,

input      wire  [15:0] HRDATA,
input      wire         HREADY,
input      wire  [1:0]  HRESP,

output           [1:0]  RESP_err,
output     reg          AHB_BUSY,
output	   reg			VALID
);

// AHB FSM States
reg [2:0] ahb_fsm_current_state;
parameter [2:0] Idle_1 = 3'b000, Read_FIC_0 = 3'b001, Read_FIC_1 = 3'b010, Read_FIC_2 = 3'b011, Read_FIC_3 = 3'b100;

parameter [31:0] ADDR = 32'h20008000;

reg   [31:0] HWDATA_int; //temporary hold the data
wire  [2:0]  HSIZE_int;

assign RESP_err = HRESP;
assign HBURST = 3'b000;
assign HPROT  = 4'b0011;
assign HSIZE  = 3'b001;//3'b010; // 32 Bit Mode

// since the current coreahblite is 32 bit, we are using Hsize=10 (32-bit), but can be changed
parameter [4:0] Data_size	= 32;

//generate
//    if (Data_size == 32)  
//        assign HSIZE_int  = 2'b10;  
//    else if (Data_size == 16) 
//        assign HSIZE_int  = 2'b01;
//    else if (Data_size == 8) 
//        assign HSIZE_int  = 2'b00;
//endgenerate

// FSM That Acts as Master on AHB Bus
// Assuming only Non-Sequential & Idle
always@(posedge HCLK, negedge HRESETn)
begin

	if(HRESETn  == 1'b0)
	    begin
	     HADDR               <=  32'h00000000;
	     HTRANS              <=  2'b00;  
	     HWRITE              <=  1'b1;
	     VALID				 <=	 1'b0;
	     HWDATA              <=  32'h00000000;
	     DATAOUT             <=  32'h00000000;
	     ahb_fsm_current_state   <=  Idle_1;
         AHB_BUSY                <=  1'b0;
	    end

	else
    	begin
	        case (ahb_fsm_current_state)
	      
	        Idle_1: //0x00
	            begin
					VALID				 <=	 1'b0;
	                if ( READ  == 1'b1)
	                  begin
	                    ahb_fsm_current_state       <=  Read_FIC_0;
                        HADDR                       <=  ADDR;   
                        HWRITE                  <=  1'b0;                    						
                        AHB_BUSY                    <=  1'b1;
	                  end
	                else
	                  begin
	                    ahb_fsm_current_state       <=  Idle_1;
	                  end
	            end

             Read_FIC_0: //0x01 					//store the address+control signals and apply to coreahblite
                begin
                    HTRANS                  <=  2'b10;
                    HWRITE                  <=  1'b1;
                    ahb_fsm_current_state   <=  Read_FIC_1;
                end
            Read_FIC_1: //0x02
                begin                   
                    if ( HREADY  == 1'b0) 			//keep the address+control signals when slave is not ready yet
                        begin
                        ahb_fsm_current_state    <=  Read_FIC_1;
                        end 
                    else   
                        begin   						// go to next state
                        HADDR                    <=  32'h00000000;  //doesn't need to keep the address+other controls any more
                        HTRANS                   <=  2'b00;
                        ahb_fsm_current_state    <=  Read_FIC_2;
                        end
                end
            Read_FIC_2: //0x03                         
                begin
                    if ( HREADY  == 1'b0)         	//waiting slave to be ready 
                        begin
                        ahb_fsm_current_state    <=  Read_FIC_2;
                        AHB_BUSY                 <=  1'b1;
                        end
                    else  							//read the data+finish the read transfer
                        begin
                        DATAOUT                  <=  HRDATA;	  
                        VALID				 	 <=	 1'b1;                       
                        ahb_fsm_current_state    <=  Read_FIC_3;
                        AHB_BUSY                 <=  1'b0;
                        end       
                end     

            Read_FIC_3: //0x04
                begin
                    
                    // if(Tx_complete == 1)begin
                        ahb_fsm_current_state <= Idle_1;
                    // end
                    // else begin
                        // ahb_fsm_current_state <= Read_FIC_3;
                    // end

                end
            endcase
	end     
end

endmodule

AHB_tb.v
`include "AHB_Bus.v"

module AHB_tb;

reg HCLK, HRESETn, READ, HREADY;
reg [15:0] HRDATA;
reg [1:0] HRESP;

wire [15:0] DATAOUT;
wire [31:0] HADDR;
wire [1:0] HTRANS;
wire HWRITE, AHB_BUSY, VALID;
wire  [2:0]  HSIZE;
wire  [2:0]  HBURST;
wire  [3:0]  HPROT;
wire   [31:0] HWDATA;
wire [1:0]  RESP_err;



AHB_BUS bus1( 
HCLK,
HRESETn,
READ,
DATAOUT,
HADDR,
HTRANS,
HWRITE,
HSIZE,
HBURST,
HPROT,
HWDATA,
HRDATA,
HREADY,
HRESP,
RESP_err,
AHB_BUSY,
VALID
);


initial begin
        $dumpfile("AHB_Bus.vcd"); 
        $dumpvars(0, AHB_tb);

        #0 HCLK = 0;
        HRESETn = 0;
        READ = 0;
        HRDATA = 0;
        HREADY = 1;
        HRESP = 0;
        #3 HRESETn = 1;
end

initial begin
        
        #0 READ = 1;

        #15 HREADY = 0;
        #40 HREADY = 1;
end

initial begin
    #55 HRDATA = 16'hABCD;
end

always #5 begin
    HCLK = ~HCLK;    
end


initial #100 $finish;


endmodule

AHB_Bus.vcd
$date
	Sat Feb 10 10:51:23 2024
$end
$version
	Icarus Verilog
$end
$timescale
	1s
$end
$scope module AHB_tb $end
$var wire 3 ! HBURST [2:0] $end
$var wire 4 " HPROT [3:0] $end
$var wire 3 # HSIZE [2:0] $end
$var wire 1 $ VALID $end
$var wire 2 % RESP_err [1:0] $end
$var wire 1 & HWRITE $end
$var wire 32 ' HWDATA [31:0] $end
$var wire 2 ( HTRANS [1:0] $end
$var wire 32 ) HADDR [31:0] $end
$var wire 16 * DATAOUT [15:0] $end
$var wire 1 + AHB_BUSY $end
$var reg 1 , HCLK $end
$var reg 16 - HRDATA [15:0] $end
$var reg 1 . HREADY $end
$var reg 1 / HRESETn $end
$var reg 2 0 HRESP [1:0] $end
$var reg 1 1 READ $end
$scope module bus1 $end
$var wire 3 2 HBURST [2:0] $end
$var wire 1 , HCLK $end
$var wire 4 3 HPROT [3:0] $end
$var wire 16 4 HRDATA [15:0] $end
$var wire 1 . HREADY $end
$var wire 1 / HRESETn $end
$var wire 2 5 HRESP [1:0] $end
$var wire 3 6 HSIZE [2:0] $end
$var wire 1 1 READ $end
$var wire 2 7 RESP_err [1:0] $end
$var parameter 32 8 ADDR $end
$var parameter 5 9 Data_size $end
$var parameter 3 : Idle_1 $end
$var parameter 3 ; Read_FIC_0 $end
$var parameter 3 < Read_FIC_1 $end
$var parameter 3 = Read_FIC_2 $end
$var parameter 3 > Read_FIC_3 $end
$var reg 1 + AHB_BUSY $end
$var reg 16 ? DATAOUT [15:0] $end
$var reg 32 @ HADDR [31:0] $end
$var reg 2 A HTRANS [1:0] $end
$var reg 32 B HWDATA [31:0] $end
$var reg 1 & HWRITE $end
$var reg 1 $ VALID $end
$var reg 3 C ahb_fsm_current_state [2:0] $end
$upscope $end
$upscope $end
$enddefinitions $end
$comment Show the parameter values. $end
$dumpall
b100 >
b11 =
b10 <
b1 ;
b0 :
b0 9
b100000000000001000000000000000 8
$end
#0
$dumpvars
b0 C
b0 B
b0 A
b0 @
b0 ?
b0 7
b1 6
b0 5
b0 4
b11 3
b0 2
11
b0 0
0/
1.
b0 -
0,
0+
b0 *
b0 )
b0 (
b0 '
1&
b0 %
0$
b1 #
b11 "
b0 !
$end
#3
1/
#5
1+
0&
b100000000000001000000000000000 )
b100000000000001000000000000000 @
b1 C
1,
#10
0,
#15
b10 C
1&
b10 (
b10 A
1,
0.
#20
0,
#25
1,
#30
0,
#35
1,
#40
0,
#45
1,
#50
0,
#55
b11 C
b0 (
b0 A
b0 )
b0 @
1,
1.
b1010101111001101 -
b1010101111001101 4
#60
0,
#65
0+
b100 C
1$
b1010101111001101 *
b1010101111001101 ?
1,
#70
0,
#75
b0 C
1,
#80
0,
#85
1+
0&
b100000000000001000000000000000 )
b100000000000001000000000000000 @
b1 C
0$
1,
#90
0,
#95
b10 C
1&
b10 (
b10 A
1,
