RS485_PSLV_Controller.v

////////////////////

module Tx_Controller(input wire clk, input wire seq_detect, input[15:0] data_in, output reg Tx_Enable, output reg Tx, output reg Tx_complete); 

    // reg[15:0] data = data_in;
    reg tx_reg = 1;
    integer i_tx = 0;
    initial Tx = 1;
    reg tx_en = 1;
    reg rst;
    initial rst = 0;
    initial Tx_complete = 0;
     initial Tx_Enable = 0;

    always @ (posedge seq_detect) begin

        Tx_Enable = 1;

    end
        
    always @ (posedge clk, posedge Tx_Enable) begin

        if(Tx_Enable == 1) begin
            // if(rst == 1) begin
            //   #10  rst = 0;
            //     i_tx = 1;
            //     Tx_complete = 0;
            // end

            // else begin
                i_tx = i_tx + 1;

                case (i_tx)
                    // 0: begin
                    //     @(posedge Tx_Enable) begin
                    //         rst = 0;
                    //     end
                    // end 
                    1 : begin
                        Tx_complete = 0;
                        tx_reg <= 0; 
                    end
                    2 : tx_reg <= data_in[0];
                    3 : tx_reg <= data_in[1];
                    4 : tx_reg <= data_in[2];
                    5 : tx_reg <= data_in[3];
                    6 : tx_reg <= data_in[4];
                    7 : tx_reg <= data_in[5];
                    8 : tx_reg <= data_in[6];
                    9 : tx_reg <= data_in[7];
                    10 : tx_reg <= 0;
                    11 : tx_reg <= 1;
                    12 : tx_reg <= 0;
                    13 : tx_reg <= data_in[8];
                    14 : tx_reg <= data_in[9];
                    15 : tx_reg <= data_in[10];
                    16 : tx_reg <= data_in[11];
                    17 : tx_reg <= data_in[12];
                    18 : tx_reg <= data_in[13];
                    19 : tx_reg <= data_in[14];
                    20 : tx_reg <= data_in[15];
                    21 : tx_reg <= 0;
                    22 : tx_reg <= 1;
                    23 : begin
                        assign rst = 1;
                        i_tx = 0;
                        Tx_complete <= 1;
                        Tx_Enable = 0;
                    end 

                    default: tx_reg <= 1;
                endcase
            // end
        end
        else begin
            @(posedge Tx_Enable) begin
                rst = 0;
            end
        end
        assign Tx = tx_reg;
    end


endmodule


module sequence_detector(
    input clk,
    input reset,
    input Rx,
    output reg detected
);

    parameter Slave_Addr = 8'h01;
    // reg seq = {1'b0, Slave_Addr, 1'b1, 1'b1};
    reg [10:0] state = 0;  // State register to store the current sequence

    always @(posedge clk or posedge reset) begin
        if (reset) begin
            state <= 0;
            detected <= 0;
        end else begin
            state <= {state[9:0], Rx};  // Shift in the new input bit
            if (state == 11'b01000000011) begin  // Check if the sequence is detected
                detected <= 1;
            end else begin
                detected <= 0;
            end
        end
    end

endmodule

module transmitter_with_detector(
    input clk,
    input Rx,
    input [15:0] byte_in,
    output reg Tx_Enable,
    output wire Tx
);

    reg reset;
    wire sequence_detected;
    wire tx_complete;
    wire tx_en;
    wire rst;

    initial reset = 0;
    initial Tx_Enable = 0;
    
    sequence_detector detector(clk, reset, Rx, sequence_detected);

    Tx_Controller t1(clk, sequence_detected, byte_in, tx_en, Tx, Tx_complete);


endmodule

RS485_PSLV_Controller_tb.v
`include "RS485_PSLV_Controller.v"

// module  top_tb;
//     reg clk;
//     reg Rx;
//     wire Tx;
//     wire tx_en_top;
 
//     top t1(clk, Rx, tx_en_top, Tx);

//     initial begin
//         $dumpfile("RS485_PSLV_Controller.vcd"); 
//         $dumpvars(0, top_tb);
//         #0 clk = 0;
//         #0 Rx = 1;
//         #18 Rx = 0;
//         #10 Rx = 1;
//         #10 Rx = 0;
//         #10 Rx = 0;
//         #10 Rx = 0;
//         #10 Rx = 0;
//         #10 Rx = 0;
//         #10 Rx = 0;
//         #10 Rx = 0;
//         #10 Rx = 1;
//         #10 Rx = 1; 
//     end

//     initial begin
//         // $dumpfile("RS485_PSLV_Controller.vcd"); 
//         // $dumpvars(0, top_tb);
//         #450 Rx = 0;
//         #10 Rx = 1;
//         #10 Rx = 0;
//         #10 Rx = 0;
//         #10 Rx = 0;
//         #10 Rx = 0;
//         #10 Rx = 0;
//         #10 Rx = 0;
//         #10 Rx = 0;
//         #10 Rx = 1;
//         #10 Rx = 1;
        
//     end

//     always #5 begin
//          clk = ~clk;
//     end

//     initial #1200 $finish;

// endmodule

// module transmitter_with_detector_tb;

//     reg clk;
//     reg  Rx;
//     reg [7:0] byte_in;
//     wire Tx_Enable;
//     wire data_out;

//     transmitter_with_detector dut(clk, Rx, byte_in, Tx_Enable, data_out);

//     initial begin
//         clk = 0;
//         Rx = 1;

//     end

//     always #5 clk = ~clk;

//     // initial begin
//     //     $dumpfile("transmitter_test.vcd");
//     //     $dumpvars(0, transmitter_with_detector_tb);

//     //     // Apply test sequence to trigger sequence detection and transmission
//     //     #30 byte_in = 8'h55;  // First byte to initiate sequence detection
//     //     #60 byte_in = 8'h01;  // Second byte to complete the sequence
//     //     #70 byte_in = 8'hAA;  // Additional byte to be transmitted
//     //     #120 $finish;
//     // end

//     initial begin
//         $dumpfile("transmitter_test.vcd");
//         $dumpvars(0, transmitter_with_detector_tb);

//         #18 Rx = 0;
//         #10 Rx = 1;
//         #10 Rx = 0;
//         #10 Rx = 0;
//         #10 Rx = 0;
//         #10 Rx = 0;
//         #10 Rx = 0;
//         #10 Rx = 0;
//         #10 Rx = 0;
//         #10 Rx = 1;
//         #10 Rx = 1;
//     end

//     initial begin
//     //     // $dumpfile("RS485_PSLV_Controller.vcd"); 
//     //     // $dumpvars(0, top_tb);
//         #400 Rx = 0;
//         #10 Rx = 1;
//         #10 Rx = 0;
//         #10 Rx = 0;
//         #10 Rx = 0;
//         #10 Rx = 0;
//         #10 Rx = 0;
//         #10 Rx = 0;
//         #10 Rx = 0;
//         #10 Rx = 1;
//         #10 Rx = 1;
        
//     end


//     initial #1200 $finish;

// endmodule


module Rx_Controller_tb;

    reg clk;
    reg rst;
    reg Rx;
    wire Tx_Enable;
    // reg [7:0] byte_in;
    wire data_out;
    reg[15:0] data = 16'h3fe0;
    // RS485_PSLV_Controller c1(clk, Tx);
// sequence_detector s1(clk, rst, Rx, Tx_Enable);
    transmitter_with_detector dut(clk, Rx, data, Tx_Enable, data_out);

    initial begin
        $dumpfile("RS485_PSLV_Controller.vcd"); 
        $dumpvars(0, Rx_Controller_tb);
        #0 clk = 0;
        #0 rst = 1;
        #0 Rx = 1;
        #10 rst = 0;
        #18 Rx = 0;
        #10 Rx = 1;
        #10 Rx = 0;
        #10 Rx = 0;
        #10 Rx = 0;
        #10 Rx = 0;
        #10 Rx = 0;
        #10 Rx = 0;
        #10 Rx = 0;
        #10 Rx = 1;
        #10 Rx = 1;        

    end

    initial begin
    //     // $dumpfile("RS485_PSLV_Controller.vcd"); 
    //     // $dumpvars(0, top_tb);
        #400 Rx = 0;
        #10 Rx = 1;
        #10 Rx = 0;
        #10 Rx = 0;
        #10 Rx = 0;
        #10 Rx = 0;
        #10 Rx = 0;
        #10 Rx = 0;
        #10 Rx = 0;
        #10 Rx = 1;
        #10 Rx = 1;
        
    end

    initial begin
        // $dumpfile("RS485_PSLV_Controller.vcd"); 
        // $dumpvars(0, top_tb);
        #730 Rx = 0;
        #10 Rx = 1;
        #10 Rx = 0;
        #10 Rx = 0;
        #10 Rx = 0;
        #10 Rx = 0;
        #10 Rx = 0;
        #10 Rx = 0;
        #10 Rx = 0;
        #10 Rx = 1;
        #10 Rx = 1;
        
    end

    always #5 begin
         clk = ~clk;
    end

    initial #1500 $finish;

endmodule


// module Tx_Controller_tb;

//     reg clk;
//     reg Tx_Enable;
//     wire Tx;
//     wire Tx_complete;

//     initial begin
//         $dumpfile("RS485_PSLV_Controller.vcd"); 
//         $dumpvars(0, Tx_Controller_tb);
//         clk = 0; 
//         Tx_Enable = 0;
//         #10 Tx_Enable = 1;
//         #250 Tx_Enable = 0;
//         #10 Tx_Enable = 1;    
//     end

//     Tx_Controller c1(clk, Tx_Enable, Tx, Tx_complete);

//     // initial begin
//         // $dumpfile("RS485_PSLV_Controller.vcd"); 
//         // $dumpvars(0, Tx_Controller_tb);

//     //     #300 tx_en = 1;

//     // end

//     // initial begin
//     //     // $dumpfile("RS485_PSLV_Controller.vcd"); 
//     //     // $dumpvars(0, Tx_Controller_tb);

//     //     #470 tx_en = 1;

//     // end

//     // assign tx_en_wire = tx_en;



//     always #5 begin
//          clk = ~clk;
//     end

//     initial #550 $finish;

// endmodule

RS485_PSLV_Controller.vcd
$date
	Fri Jan 19 13:28:39 2024
$end
$version
	Icarus Verilog
$end
$timescale
	1s
$end
$scope module Rx_Controller_tb $end
$var wire 1 ! data_out $end
$var wire 1 " Tx_Enable $end
$var reg 1 # Rx $end
$var reg 1 $ clk $end
$var reg 16 % data [15:0] $end
$var reg 1 & rst $end
$scope module dut $end
$var wire 1 # Rx $end
$var wire 16 ' byte_in [15:0] $end
$var wire 1 $ clk $end
$var wire 1 ( tx_en $end
$var wire 1 ) sequence_detected $end
$var wire 1 * Tx_complete $end
$var wire 1 ! Tx $end
$var reg 1 " Tx_Enable $end
$var reg 1 + reset $end
$scope module detector $end
$var wire 1 # Rx $end
$var wire 1 $ clk $end
$var wire 1 + reset $end
$var parameter 8 , Slave_Addr $end
$var reg 1 ) detected $end
$var reg 11 - state [10:0] $end
$upscope $end
$scope module t1 $end
$var wire 1 $ clk $end
$var wire 16 . data_in [15:0] $end
$var wire 1 ) seq_detect $end
$var reg 1 ! Tx $end
$var reg 1 ( Tx_Enable $end
$var reg 1 * Tx_complete $end
$var reg 1 / rst $end
$var reg 1 0 tx_en $end
$var reg 1 1 tx_reg $end
$var integer 32 2 i_tx [31:0] $end
$upscope $end
$upscope $end
$upscope $end
$enddefinitions $end
$comment Show the parameter values. $end
$dumpall
b1 ,
$end
#0
$dumpvars
b0 2
11
10
0/
b11111111100000 .
b0 -
0+
0*
x)
0(
b11111111100000 '
1&
b11111111100000 %
0$
1#
0"
1!
$end
#5
0)
b1 -
1$
#10
0$
0&
#15
b11 -
1$
#20
0$
#25
b111 -
1$
#28
0#
#30
0$
#35
b1110 -
1$
#38
1#
#40
0$
#45
b11101 -
1$
#48
0#
#50
0$
#55
b111010 -
1$
#60
0$
#65
b1110100 -
1$
#70
0$
#75
b11101000 -
1$
#80
0$
#85
b111010000 -
1$
#90
0$
#95
b1110100000 -
1$
#100
0$
#105
b11101000000 -
1$
#110
0$
#115
b11010000000 -
1$
#118
1#
#120
0$
#125
b10100000001 -
1$
#130
0$
#135
b1000000011 -
1$
#140
0$
#145
1(
1)
b10000000111 -
1$
#150
0$
#155
0)
b1111 -
0!
01
b1 2
1$
#160
0$
#165
b11111 -
b10 2
1$
#170
0$
#175
b111111 -
b11 2
1$
#180
0$
#185
b1111111 -
b100 2
1$
#190
0$
#195
b11111111 -
b101 2
1$
#200
0$
#205
b111111111 -
b110 2
1$
#210
0$
#215
b1111111111 -
1!
11
b111 2
1$
#220
0$
#225
b11111111111 -
b1000 2
1$
#230
0$
#235
b1001 2
1$
#240
0$
#245
0!
01
b1010 2
1$
#250
0$
#255
1!
11
b1011 2
1$
#260
0$
#265
0!
01
b1100 2
1$
#270
0$
#275
1!
11
b1101 2
1$
#280
0$
#285
b1110 2
1$
#290
0$
#295
b1111 2
1$
#300
0$
#305
b10000 2
1$
#310
0$
#315
b10001 2
1$
#320
0$
#325
b10010 2
1$
#330
0$
#335
0!
01
b10011 2
1$
#340
0$
#345
b10100 2
1$
#350
0$
#355
b10101 2
1$
#360
0$
#365
1!
11
b10110 2
1$
#370
0$
#375
1*
0(
1/
b0 2
1$
#380
0$
#385
1$
#390
0$
#395
1$
#400
0$
0#
#405
b11111111110 -
1$
#410
0$
1#
#415
b11111111101 -
1$
#420
0$
0#
#425
b11111111010 -
1$
#430
0$
#435
b11111110100 -
1$
#440
0$
#445
b11111101000 -
1$
#450
0$
#455
b11111010000 -
1$
#460
0$
#465
b11110100000 -
1$
#470
0$
#475
b11101000000 -
1$
#480
0$
#485
b11010000000 -
1$
#490
0$
1#
#495
b10100000001 -
1$
#500
0$
#505
b1000000011 -
1$
#510
0$
#515
1(
1)
b10000000111 -
1$
#520
0$
#525
0)
b1111 -
0!
01
0*
b1 2
1$
#530
0$
#535
b11111 -
b10 2
1$
#540
0$
#545
b111111 -
b11 2
1$
#550
0$
#555
b1111111 -
b100 2
1$
#560
0$
#565
b11111111 -
b101 2
1$
#570
0$
#575
b111111111 -
b110 2
1$
#580
0$
#585
b1111111111 -
1!
11
b111 2
1$
#590
0$
#595
b11111111111 -
b1000 2
1$
#600
0$
#605
b1001 2
1$
#610
0$
#615
0!
01
b1010 2
1$
#620
0$
#625
1!
11
b1011 2
1$
#630
0$
#635
0!
01
b1100 2
1$
#640
0$
#645
1!
11
b1101 2
1$
#650
0$
#655
b1110 2
1$
#660
0$
#665
b1111 2
1$
#670
0$
#675
b10000 2
1$
#680
0$
#685
b10001 2
1$
#690
0$
#695
b10010 2
1$
#700
0$
#705
0!
01
b10011 2
1$
#710
0$
#715
b10100 2
1$
#720
0$
#725
b10101 2
1$
#730
0$
0#
#735
b11111111110 -
1!
11
b10110 2
1$
#740
0$
1#
#745
b11111111101 -
1*
0(
b0 2
1$
#750
0$
0#
#755
b11111111010 -
1$
#760
0$
#765
b11111110100 -
1$
#770
0$
#775
b11111101000 -
1$
#780
0$
#785
b11111010000 -
1$
#790
0$
#795
b11110100000 -
1$
#800
0$
#805
b11101000000 -
1$
#810
0$
#815
b11010000000 -
1$
#820
0$
1#
#825
b10100000001 -
1$
#830
0$
#835
b1000000011 -
1$
#840
0$
#845
1(
1)
b10000000111 -
1$
#850
0$
#855
0)
b1111 -
0!
01
0*
b1 2
1$
#860
0$
#865
b11111 -
b10 2
1$
#870
0$
#875
b111111 -
b11 2
1$
#880
0$
#885
b1111111 -
b100 2
1$
#890
0$
#895
b11111111 -
b101 2
1$
#900
0$
#905
b111111111 -
b110 2
1$
#910
0$
#915
b1111111111 -
1!
11
b111 2
1$
#920
0$
#925
b11111111111 -
b1000 2
1$
#930
0$
#935
b1001 2
1$
#940
0$
#945
0!
01
b1010 2
1$
#950
0$
#955
1!
11
b1011 2
1$
#960
0$
#965
0!
01
b1100 2
1$
#970
0$
#975
1!
11
b1101 2
1$
#980
0$
#985
b1110 2
1$
#990
0$
#995
b1111 2
1$
#1000
0$
#1005
b10000 2
1$
#1010
0$
#1015
b10001 2
1$
#1020
0$
#1025
b10010 2
1$
#1030
0$
#1035
0!
01
b10011 2
1$
#1040
0$
#1045
b10100 2
1$
#1050
0$
#1055
b10101 2
1$
#1060
0$
#1065
1!
11
b10110 2
1$
#1070
0$
#1075
1*
0(
b0 2
1$
